json_payload_validator
