Metadata-Version: 1.1
Name: json-payload-validator
Version: 0.1.0
Summary: JSON validator package based on jsonschema that returns nicer validation errors for end users
Home-page: https://github.com/thiagomarini/json-payload-validator
Author: Thiago Marini
Author-email: UNKNOWN
License: MIT
Keywords: json schema payload validation
Platform: UNKNOWN
Classifier: Programming Language :: Python :: 2.7
Classifier: Programming Language :: Python :: 3
Classifier: Programming Language :: Python :: 3.4
Classifier: Programming Language :: Python :: 3.5
Classifier: Programming Language :: Python :: 3.6
Classifier: License :: OSI Approved :: MIT License
Classifier: Operating System :: OS Independent
